OpenSMOG/OpenSMOG.py
OpenSMOG/OpenSMOG_Reporter.py
OpenSMOG/__init__.py
OpenSMOG/share/openSMOG.xsd
OpenSMOG-0.0.1.dist-info/LICENSE
OpenSMOG-0.0.1.dist-info/METADATA
OpenSMOG-0.0.1.dist-info/WHEEL
OpenSMOG-0.0.1.dist-info/entry_points.txt
OpenSMOG-0.0.1.dist-info/top_level.txt
OpenSMOG-0.0.1.dist-info/zip-safe
OpenSMOG-0.0.1.dist-info/RECORD
