Metadata-Version: 2.1
Name: OpenSMOG
Version: 0.0.1
Summary: Structure-based Models for Biomolecules using OpenMM
Home-page: https://github.com/junioreif/OpenSMOG
Author: ['Antonio Bento de Oliveira Junior', 'Vinicius de Godoi Contessoto']
Author-email: antonio.oliveira@rice.edu,contessoto@rice.edu
License: UNKNOWN
Platform: UNKNOWN
Classifier: License :: OSI Approved :: GNU General Public License v3 (GPLv3)
Classifier: Operating System :: OS Independent
Classifier: Programming Language :: Python :: 3.6
Classifier: Programming Language :: Python :: 3.7
Classifier: Programming Language :: Python :: 3.8
Classifier: Topic :: Software Development :: Libraries :: Python Modules
Classifier: Natural Language :: English
Requires-Dist: numpy
Requires-Dist: lxml
